olsapy/__init__.py
olsapy/calculator.py
olsapy/data.py
olsapy/olsa.py
olsapy/plot.py
olsapy-2.0.1.dist-info/LICENSE.txt
olsapy-2.0.1.dist-info/METADATA
olsapy-2.0.1.dist-info/WHEEL
olsapy-2.0.1.dist-info/top_level.txt
olsapy-2.0.1.dist-info/RECORD
