Metadata-Version: 2.1
Name: olsapy
Version: 2.0.1
Summary: a package for orthogonal linear separation analysis (OLSA)
Home-page: https://github.com/mizuno-group
Author: tadahaya mizuno
Author-email: tadahaya@gmail.com
License: MIT
Keywords: omics,bioinformatics,transcriptome,chemoinformatics
Platform: UNKNOWN
Classifier: Development Status :: 5 - Production/Stable
Classifier: Environment :: Win32 (MS Windows)
Classifier: Framework :: IPython
Classifier: Intended Audience :: Science/Research
Classifier: Operating System :: Microsoft :: Windows :: Windows 10
Classifier: Programming Language :: Python :: 3
Classifier: Topic :: Scientific/Engineering :: Bio-Informatics
Requires-Python: >=3.6
Requires-Dist: numpy
Requires-Dist: scipy
Requires-Dist: pandas
Requires-Dist: matplotlib
